{"json_modified": "2014-03-25T10:13:54.422339", "slug": "Web/API/element.dir", "tags": ["\u8981\u66f4\u65b0"], "locale": "ja", "title": "element.dir", "translations": [{"locale": "zh-CN", "url": "/zh-CN/docs/DOM/element.dir", "last_edit": "2012-04-26T14:21:51", "title": "element.dir"}, {"locale": "en-US", "url": "/en-US/docs/Web/API/HTMLElement.dir", "last_edit": "2014-03-21T04:26:32", "title": "HTMLElement.dir"}, {"locale": "pl", "url": "/pl/docs/DOM/element.dir", "last_edit": "2013-02-21T11:30:02", "title": "element.dir"}, {"locale": "fr", "url": "/fr/docs/DOM/element.dir", "last_edit": "2013-05-11T10:34:26", "title": "element.dir"}], "modified": "2014-03-25T10:13:54", "label": "element.dir", "url": "/ja/docs/Web/API/element.dir", "last_edit": "2013-05-18T03:14:38", "summary": "<code><strong>dir</strong></code>\u00a0\u5c5e\u6027\u306f\u3001\u8981\u7d20\u306e\u30c6\u30ad\u30b9\u30c8\u306e\u66f8\u304d\u8fbc\u307f\u65b9\u5411\u3092\u53d6\u5f97\u307e\u305f\u306f\u8a2d\u5b9a\u3057\u307e\u3059\u3002", "sections": [{"id": "Quick_Links", "title": "DOM \u30ea\u30d5\u30a1\u30ec\u30f3\u30b9 element Properties Methods"}, {"id": "Summary", "title": "\u6982\u8981"}, {"id": "Syntax_and_values", "title": "\u69cb\u6587\u3068\u5024"}, {"id": "Example", "title": "\u4f8b"}, {"id": "Notes", "title": "\u6ce8\u8a18"}, {"id": "Specification", "title": "\u4ed5\u69d8"}], "id": 4863, "review_tags": []}