{"json_modified": "2014-03-25T10:02:11.580072", "slug": "Web/API/Node.replaceChild", "tags": ["Gecko DOM Reference", "DOM", "Node", "Gecko"], "locale": "ja", "title": "Node.replaceChild", "translations": [{"locale": "zh-CN", "url": "/zh-CN/docs/DOM/Node.replaceChild", "last_edit": "2012-05-16T15:09:25", "title": "Node.replaceChild"}, {"locale": "en-US", "url": "/en-US/docs/Web/API/Node.replaceChild", "last_edit": "2013-09-28T12:11:57", "title": "Node.replaceChild"}, {"locale": "pl", "url": "/pl/docs/DOM/element.replaceChild", "last_edit": "2008-08-01T09:04:20", "title": "element.replaceChild"}, {"locale": "fr", "url": "/fr/docs/DOM/element.replaceChild", "last_edit": "2008-08-01T09:04:00", "title": "element.replaceChild"}, {"locale": "de", "url": "/de/docs/DOM/Node.replaceChild", "last_edit": "2012-10-19T01:45:40", "title": "Node.replaceChild"}], "modified": "2014-03-25T10:02:11", "label": "Node.replaceChild", "url": "/ja/docs/Web/API/Node.replaceChild", "last_edit": "2013-05-18T21:15:54", "summary": "\u6307\u5b9a\u30ce\u30fc\u30c9\u306e\u5b50\u30ce\u30fc\u30c9\u3092\u5225\u306e\u30ce\u30fc\u30c9\u306b\u7f6e\u304d\u63db\u3048\u307e\u3059\u3002", "sections": [{"id": "Quick_Links", "title": "DOM \u30ea\u30d5\u30a1\u30ec\u30f3\u30b9 Node Properties Methods"}, {"id": "Summary", "title": "\u6982\u8981"}, {"id": "Syntax", "title": "\u69cb\u6587"}, {"id": "Example", "title": "\u4f8b"}, {"id": "Specification", "title": "\u4ed5\u69d8\u66f8"}, {"id": "See_also", "title": "\u95a2\u9023\u60c5\u5831"}], "id": 32973, "review_tags": []}